lets_learn_py/__init__.py
lets_learn_py-0.1.dist-info/METADATA
lets_learn_py-0.1.dist-info/RECORD
lets_learn_py-0.1.dist-info/WHEEL
lets_learn_py-0.1.dist-info/top_level.txt
