Metadata-Version: 2.1
Name: lets-learn-py
Version: 0.1
Summary: Welcome to the User
Home-page: https://github.com/learn-with-abhi/lets_learn_py
Author: Abhilash R
Author-email: smile_with_abhi@hotmail.com
License: MIT
Platform: UNKNOWN
Classifier: Programming Language :: Python :: 3
Classifier: License :: OSI Approved :: MIT License
Classifier: Operating System :: OS Independent
